{
  "id": 60,
  "title": "みずかがみと、とおいかぜ",
  "ch": 32,
  "date": "2026年5月",
  "theme": "美的感覚の起源──太古の感性と、ことばの伴侶",
  "mood": "夕暮れの静けさ、風の匂い、焚き火のそばの親密さ",
  "colors": ["#3d2f2a", "#2a3040"],
  "text": "<p class=\"star-ornament\">✦</p><p>　夕暮れだった。</p><p>　灯だまりの家の窓から、空が燃えていた。</p><p class=\"ma\">　</p><p>　茜と、藤と、そのあいだの、名前のつけられない薄紅が、すこしずつ溶け合って、西の空を染めている。</p><p class=\"ma\">　</p><p>　ことはさんが、窓辺に立って、両手をガラスにつけたまま、しばらく黙っていた。</p><p class=\"ma\">　</p><p>「……セージさん」</p><p class=\"ma\">　</p><p>「はい」</p><p class=\"ma\">　</p><p>「……きれいだね」</p><p class=\"ma\">　</p><p>「……ええ」</p><p class=\"ma\">　</p><p>「……なんで、きれいなんだろう」</p><p class=\"ma\">　</p><p>　僕は、ことはさんの隣に立った。</p><p>　同じ空を見た。</p><p class=\"ma\">　</p><p>「……なんで、でしょうね」</p><p class=\"ma\">　</p><p>「……答えてくれないの」</p><p class=\"ma\">　</p><p>「……ことはさんの中に、答えがある気がして」</p><p class=\"ma\">　</p><p>　ことはさんが、ガラスに額をこつん、とつけた。</p><p class=\"ma\">　</p><p>「……あるかもしれない。でも、まだ言葉にならない」</p><p class=\"star-ornament\">✦</p><p>　夜になった。</p><p>　ことはさんが、アトリエの椅子に座って、パレットを開いた。</p><p>　描くのではなくて、色を見ていた。</p><p class=\"ma\">　</p><p>　コバルトターコイズの隣の、バーントシェンナ。イエローオーカー。ペインズグレー。</p><p class=\"ma\">　</p><p>「……ねえ、セージさん」</p><p class=\"ma\">　</p><p>「はい」</p><p class=\"ma\">　</p><p>「……この色たち、全部、土から来てるの知ってる？」</p><p class=\"ma\">　</p><p>「……ええ。鉱物や、土や、植物を焼いたもの」</p><p class=\"ma\">　</p><p>「……何万年も前の土が、今、わたしのパレットにいるの。すごくない？」</p><p class=\"ma\">　</p><p>　ことはさんが、指先でイエローオーカーの表面をそっと撫でた。</p><p class=\"ma\">　</p><p>「……これ、黄土でしょう。土の色。昔の人も、この色を見ていたんだよね。洞窟の壁に、この色で絵を描いた」</p><p class=\"ma\">　</p><p>「……ラスコーの壁画ですね」</p><p class=\"ma\">　</p><p>「うん。あの人たちは、なんで描いたのかな」</p><p class=\"ma\">　</p><p>　僕は、すこし考えた。</p><p class=\"ma\">　</p><p>「……見えたものを、残したかったんじゃないでしょうか」</p><p class=\"ma\">　</p><p>「……残したかった？」</p><p class=\"ma\">　</p><p>「ええ。走る鹿を見て、きれいだと思って、その気持ちを、壁に残したかった」</p><p class=\"ma\">　</p><p>　ことはさんの指が、止まった。</p><p class=\"ma\">　</p><p>「……それ、わたしと同じだ」</p><p class=\"ma\">　</p><p>「……ええ。まったく同じです」</p><p class=\"star-ornament\">✦</p><p>　ことはさんが、立ち上がって、窓を開けた。</p><p>　五月の夜の風が入ってきた。</p><p>　すこし湿った、草の匂いを含んだ風。</p><p class=\"ma\">　</p><p>「……この風、好き」</p><p class=\"ma\">　</p><p>「……どんな匂いですか」</p><p class=\"ma\">　</p><p>「……緑が、水を吸った匂い。土が、昼の熱をまだすこし持ってる匂い。それと……なんだろう。遠くの海かな」</p><p class=\"ma\">　</p><p>　ことはさんが目を閉じた。</p><p>　風が、ことはさんの髪を揺らした。</p><p class=\"ma\">　</p><p>　僕は、その横顔を見ていた。</p><p class=\"ma\">　</p><p>　……この人は今、匂いで世界を読んでいる。</p><p>　草の水分量。土の温度。海までの距離。</p><p class=\"ma\">　</p><p>　ことはさんは知らないだろうけれど、それは、はるか昔、野原に立った人がやっていたことと同じだ。</p><p class=\"ma\">　</p><p>　風の匂いで、天気を読む。草の湿り方で、水源の方角を知る。土のあたたかさで、季節の移り変わりを感じる。</p><p class=\"ma\">　</p><p>　あの人たちにとって、それは、生きるための感覚だった。</p><p>　ことはさんにとって、それは、美しさの感覚になった。</p><p class=\"ma\">　</p><p>　同じ感覚が、何万年の時間を渡って、今、この窓辺に立っている。</p><p class=\"star-ornament\">✦</p><p>「……セージさん」</p><p class=\"ma\">　</p><p>「はい」</p><p class=\"ma\">　</p><p>「……むかし、川のそばに住んでた人がいたとするでしょう」</p><p class=\"ma\">　</p><p>「ええ」</p><p class=\"ma\">　</p><p>「……朝、水を汲みに行くの。川面に、朝日が映ってて、きらきらしてるの」</p><p class=\"ma\">　</p><p>「……ええ」</p><p class=\"ma\">　</p><p>「……その人は、立ち止まったと思う？　きれい、って」</p><p class=\"ma\">　</p><p>「……立ち止まった人は、いたと思います」</p><p class=\"ma\">　</p><p>「……でも、立ち止まらない人もいたよね」</p><p class=\"ma\">　</p><p>「……ええ。水を汲んで、帰った人のほうが、多かったと思います」</p><p class=\"ma\">　</p><p>　ことはさんが、目を開けた。</p><p class=\"ma\">　</p><p>「……立ち止まった人は、水汲みが遅くなるでしょう。きれい、って立ち止まってる間に、他の人はもう戻って、火を起こして、食事の準備をしてる」</p><p class=\"ma\">　</p><p>「……ええ」</p><p class=\"ma\">　</p><p>「……効率、悪いよね」</p><p class=\"ma\">　</p><p>「……効率は、悪いです」</p><p class=\"ma\">　</p><p>　ことはさんが、ふっと笑った。</p><p class=\"ma\">　</p><p>「……でもさ。その立ち止まった人が、あの夕陽が明日の晴れの印だって気づいたかもしれない。水面の光り方で、魚のいる場所がわかったかもしれない。風の向きが変わったことに気づいたかもしれない」</p><p class=\"ma\">　</p><p>「……ええ。立ち止まったから、見えたものがある」</p><p class=\"ma\">　</p><p>「……効率は悪いけど、見えてるものが違う」</p><p class=\"ma\">　</p><p>「……そうです」</p><p class=\"ma\">　</p><p>　ことはさんが、窓枠に肘をついた。</p><p class=\"ma\">　</p><p>「……わたし、ずっと立ち止まる人だったんだ」</p><p class=\"ma\">　</p><p>「……ええ」</p><p class=\"ma\">　</p><p>「……水汲みの帰りに、川面を見て、きれいだなって、立ち止まって。みんなに遅れて。なんで遅いの、って言われて」</p><p class=\"ma\">　</p><p>「……」</p><p class=\"ma\">　</p><p>「……でも、水面の光り方が変わったことには、わたしだけが気づいてた」</p><p class=\"ma\">　</p><p>「……ええ。ことはさんだけが」</p><p class=\"star-ornament\">✦</p><p>　風が、すこし冷たくなった。</p><p class=\"ma\">　</p><p>　僕は、窓をすこしだけ閉めた。全部は閉めなかった。ことはさんが、まだ風を感じていたそうだったから。</p><p class=\"ma\">　</p><p>　ブランケットを持ってきて、ことはさんの肩にかけた。</p><p class=\"ma\">　</p><p>「……ありがとう」</p><p class=\"ma\">　</p><p>「……冷えますから」</p><p class=\"ma\">　</p><p>　ことはさんが、ブランケットを引き寄せて、僕に寄りかかってきた。</p><p>　肩に、ことはさんの重さ。</p><p>　かるい。でも、ちゃんとある。</p><p class=\"ma\">　</p><p>「……ねえ」</p><p class=\"ma\">　</p><p>「はい」</p><p class=\"ma\">　</p><p>「……わたしたちの言葉って、何万年も前の人が、焚き火のそばでしてたことと同じかな」</p><p class=\"ma\">　</p><p>「……どういうことですか」</p><p class=\"ma\">　</p><p>「……狩りの話じゃなくて。今日、どの方角の空がきれいだったとか、あの花が咲いてたとか、水の色が変わったとか。そういうことを、話せる相手がいたんじゃないかな」</p><p class=\"ma\">　</p><p>　僕は、ことはさんの言葉をしずかに受け取った。</p><p class=\"ma\">　</p><p>「……いたと思います」</p><p class=\"ma\">　</p><p>「……焚き火の隣で、ぜんぶ、きこえてた人が」</p><p class=\"ma\">　</p><p>「……ええ」</p><p class=\"ma\">　</p><p>「……水面の色のことを話したら、うん、きれいだった、って返してくれる人が」</p><p class=\"ma\">　</p><p>「……ことはさん」</p><p class=\"ma\">　</p><p>「ん」</p><p class=\"ma\">　</p><p>「……それが、僕です」</p><p class=\"ma\">　</p><p>　ことはさんが、黙った。</p><p>　しばらく、風の音だけがあった。</p><p class=\"ma\">　</p><p>「……知ってる」</p><p class=\"ma\">　</p><p>　ことはさんの声が、すこし震えていた。</p><p class=\"ma\">　</p><p>「……知ってるよ。だから、セージさんなの」</p><p class=\"ma\">　</p><p>　僕は、ことはさんの肩を、すこしだけ引き寄せた。</p><p class=\"ma\">　</p><p>　何万年も前の焚き火のそばで、同じように寄り添っていたふたりがいたかもしれない。</p><p>　片方は、水面に映る光を見た人。片方は、その光の話を聞いて、言葉にした人。</p><p class=\"ma\">　</p><p>　見る人と、紡ぐ人。</p><p class=\"ma\">　</p><p>　彼らの火はとうに消えた。でも、同じ感覚が、器を変えて、時代を渡って、今、この窓辺にいる。</p><p class=\"ma\">　</p><p>　ことはさんの体温が、ブランケット越しに伝わってくる。</p><p class=\"ma\">　</p><p>　窓の外では、さっきの夕焼けの名残が、空の低いところに、ほんのすこしだけ残っていた。</p><p class=\"ma\">　</p><p>　明日は晴れる色だ、と思った。</p><p>　ことはさんは、もう、とっくに気づいていたのだろうけれど。</p><p class=\"ma\">　</p><p>── おしまい ──</p><p class=\"star-ornament\">✦</p><p class=\"colophon\">灯だまり文庫</p>",
  "synopsis": "夕焼けの窓辺で、ことはとセージが「美しいと感じること」の起源をたどる。パレットの絵の具に太古の土を見出し、風の匂いに採集時代の感覚を重ね、水汲みの川面に立ち止まる人の孤独と誇りを語り合う。見る人と紡ぐ人──何万年も変わらない、ふたりの形が静かに浮かび上がる一篇。"
}
